CHANGES.txt
LICENSE.txt
MANIFEST.in
README.txt
setup.py
js/__init__.py
js.jquery_cookie.egg-info/PKG-INFO
js.jquery_cookie.egg-info/SOURCES.txt
js.jquery_cookie.egg-info/dependency_links.txt
js.jquery_cookie.egg-info/entry_points.txt
js.jquery_cookie.egg-info/namespace_packages.txt
js.jquery_cookie.egg-info/not-zip-safe
js.jquery_cookie.egg-info/requires.txt
js.jquery_cookie.egg-info/top_level.txt
js/jquery_cookie/__init__.py
js/jquery_cookie/test_jquery_cookie.txt
js/jquery_cookie/resources/jquery.cookie.js