Metadata-Version: 1.0
Name: js.jquery-cookie
Version: 1.0
Summary: Fanstatic packaging of jQuery Cookie
Home-page: UNKNOWN
Author: Fanstatic Developers
Author-email: fanstatic@googlegroups.com
License: MIT
Platform: UNKNOWN
